dyno_dino/__init__.py
dyno_dino/dynamodb.py
dyno_dino-1.0.8.dist-info/METADATA
dyno_dino-1.0.8.dist-info/WHEEL
dyno_dino-1.0.8.dist-info/top_level.txt
dyno_dino-1.0.8.dist-info/RECORD
